[
  {
    "case_start": "2025-12-31T08:14:00",
    "case_end": "2025-12-31T10:02:00",
    "case_status": "Complete",
    "case_procedure": "Coronary artery bypass graft",
    "session_start": "2025-12-31T08:30:00",
    "session_end": "2025-12-31T17:30:00",
    "session_theatre": "Theatre 1",
    "session_key": "THR1_ALLDAY",
    "last_refresh_dttm": "2025-12-31T15:30:00"
  },
  {
    "case_start": "2025-12-31T10:05:00",
    "case_end": "2025-12-31T11:54:00",
    "case_status": "Complete",
    "case_procedure": "Mitral valve repair",
    "session_start": "2025-12-31T08:30:00",
    "session_end": "2025-12-31T17:30:00",
    "session_theatre": "Theatre 1",
    "session_key": "THR1_ALLDAY",
    "last_refresh_dttm": "2025-12-31T15:30:00"
  },
  {
    "case_start": "2025-12-31T12:12:00",
    "case_end": "2025-12-31T14:09:00",
    "case_status": "Complete",
    "case_procedure": "Aortic valve replacement",
    "session_start": "2025-12-31T08:30:00",
    "session_end": "2025-12-31T17:30:00",
    "session_theatre": "Theatre 1",
    "session_key": "THR1_ALLDAY",
    "last_refresh_dttm": "2025-12-31T15:30:00"
  },
  {
    "case_start": null,
    "case_end": null,
    "case_status": null,
    "case_procedure": "Atrial septal defect closure",
    "session_start": "2025-12-31T08:30:00",
    "session_end": "2025-12-31T17:30:00",
    "session_theatre": "Theatre 1",
    "session_key": "THR1_ALLDAY",
    "last_refresh_dttm": "2025-12-31T15:30:00"
  },
  {
    "case_start": "2025-12-31T14:58:00",
    "case_end": null,
    "case_status": "In Progress",
    "case_procedure": "Left atrial appendage ligation",
    "session_start": "2025-12-31T08:30:00",
    "session_end": "2025-12-31T17:30:00",
    "session_theatre": "Theatre 1",
    "session_key": "THR1_ALLDAY",
    "last_refresh_dttm": "2025-12-31T15:30:00"
  },
  {
    "case_start": "2025-12-31T08:19:00",
    "case_end": "2025-12-31T10:09:00",
    "case_status": "Complete",
    "case_procedure": "Total thyroidectomy",
    "session_start": "2025-12-31T08:30:00",
    "session_end": "2025-12-31T17:00:00",
    "session_theatre": "Theatre 2",
    "session_key": "THR2_ALLDAY",
    "last_refresh_dttm": "2025-12-31T15:30:00"
  },
  {
    "case_start": null,
    "case_end": null,
    "case_status": null,
    "case_procedure": "Parotidectomy",
    "session_start": "2025-12-31T08:30:00",
    "session_end": "2025-12-31T17:00:00",
    "session_theatre": "Theatre 2",
    "session_key": "THR2_ALLDAY",
    "last_refresh_dttm": "2025-12-31T15:30:00"
  },
  {
    "case_start": "2025-12-31T11:34:00",
    "case_end": "2025-12-31T12:56:00",
    "case_status": "Complete",
    "case_procedure": "Neck dissection",
    "session_start": "2025-12-31T08:30:00",
    "session_end": "2025-12-31T17:00:00",
    "session_theatre": "Theatre 2",
    "session_key": "THR2_ALLDAY",
    "last_refresh_dttm": "2025-12-31T15:30:00"
  },
  {
    "case_start": "2025-12-31T13:04:00",
    "case_end": "2025-12-31T14:07:00",
    "case_status": "Complete",
    "case_procedure": "Microlaryngoscopy and biopsy",
    "session_start": "2025-12-31T08:30:00",
    "session_end": "2025-12-31T17:00:00",
    "session_theatre": "Theatre 2",
    "session_key": "THR2_ALLDAY",
    "last_refresh_dttm": "2025-12-31T15:30:00"
  },
  {
    "case_start": "2025-12-31T14:27:00",
    "case_end": null,
    "case_status": "In Progress",
    "case_procedure": "Hemiglossectomy",
    "session_start": "2025-12-31T08:30:00",
    "session_end": "2025-12-31T17:00:00",
    "session_theatre": "Theatre 2",
    "session_key": "THR2_ALLDAY",
    "last_refresh_dttm": "2025-12-31T15:30:00"
  },
  {
    "case_start": "2025-12-31T08:29:00",
    "case_end": "2025-12-31T09:35:00",
    "case_status": "Complete",
    "case_procedure": "Functional endoscopic sinus surgery",
    "session_start": "2025-12-31T08:30:00",
    "session_end": "2025-12-31T12:45:00",
    "session_theatre": "Theatre 3",
    "session_key": "THR3_AM",
    "last_refresh_dttm": "2025-12-31T15:30:00"
  },
  {
    "case_start": "2025-12-31T09:26:00",
    "case_end": "2025-12-31T10:37:00",
    "case_status": "Complete",
    "case_procedure": "Septoplasty",
    "session_start": "2025-12-31T08:30:00",
    "session_end": "2025-12-31T12:45:00",
    "session_theatre": "Theatre 3",
    "session_key": "THR3_AM",
    "last_refresh_dttm": "2025-12-31T15:30:00"
  },
  {
    "case_start": "2025-12-31T10:41:00",
    "case_end": "2025-12-31T11:53:00",
    "case_status": "Complete",
    "case_procedure": "Tonsillectomy",
    "session_start": "2025-12-31T08:30:00",
    "session_end": "2025-12-31T12:45:00",
    "session_theatre": "Theatre 3",
    "session_key": "THR3_AM",
    "last_refresh_dttm": "2025-12-31T15:30:00"
  },
  {
    "case_start": null,
    "case_end": null,
    "case_status": null,
    "case_procedure": "Tympanoplasty",
    "session_start": "2025-12-31T13:30:00",
    "session_end": "2025-12-31T17:45:00",
    "session_theatre": "Theatre 3",
    "session_key": "THR3_PM",
    "last_refresh_dttm": "2025-12-31T15:30:00"
  },
  {
    "case_start": "2025-12-31T15:08:00",
    "case_end": null,
    "case_status": "In Progress",
    "case_procedure": "Mastoidectomy",
    "session_start": "2025-12-31T13:30:00",
    "session_end": "2025-12-31T17:45:00",
    "session_theatre": "Theatre 3",
    "session_key": "THR3_PM",
    "last_refresh_dttm": "2025-12-31T15:30:00"
  },
  {
    "case_start": "2025-12-31T08:39:00",
    "case_end": "2025-12-31T10:18:00",
    "case_status": "Complete",
    "case_procedure": "Craniotomy for tumour resection",
    "session_start": "2025-12-31T08:30:00",
    "session_end": "2025-12-31T12:45:00",
    "session_theatre": "Theatre 4",
    "session_key": "THR4_AM",
    "last_refresh_dttm": "2025-12-31T15:30:00"
  },
  {
    "case_start": "2025-12-31T10:21:00",
    "case_end": "2025-12-31T11:27:00",
    "case_status": "Complete",
    "case_procedure": "Ventriculoperitoneal shunt revision",
    "session_start": "2025-12-31T08:30:00",
    "session_end": "2025-12-31T12:45:00",
    "session_theatre": "Theatre 4",
    "session_key": "THR4_AM",
    "last_refresh_dttm": "2025-12-31T15:30:00"
  },
  {
    "case_start": "2025-12-31T11:34:00",
    "case_end": "2025-12-31T12:21:00",
    "case_status": "Complete",
    "case_procedure": "Burr hole evacuation of subdural haematoma",
    "session_start": "2025-12-31T08:30:00",
    "session_end": "2025-12-31T12:45:00",
    "session_theatre": "Theatre 4",
    "session_key": "THR4_AM",
    "last_refresh_dttm": "2025-12-31T15:30:00"
  },
  {
    "case_start": "2025-12-31T12:32:00",
    "case_end": "2025-12-31T13:39:00",
    "case_status": "Complete",
    "case_procedure": "Microdiscectomy",
    "session_start": "2025-12-31T08:30:00",
    "session_end": "2025-12-31T12:45:00",
    "session_theatre": "Theatre 4",
    "session_key": "THR4_AM",
    "last_refresh_dttm": "2025-12-31T15:30:00"
  },
  {
    "case_start": "2025-12-31T13:19:00",
    "case_end": "2025-12-31T14:10:00",
    "case_status": "Complete",
    "case_procedure": "Lumbar decompression",
    "session_start": "2025-12-31T13:30:00",
    "session_end": "2025-12-31T17:45:00",
    "session_theatre": "Theatre 4",
    "session_key": "THR4_PM",
    "last_refresh_dttm": "2025-12-31T15:30:00"
  },
  {
    "case_start": "2025-12-31T14:17:00",
    "case_end": null,
    "case_status": "In Progress",
    "case_procedure": "Anterior cervical discectomy and fusion",
    "session_start": "2025-12-31T13:30:00",
    "session_end": "2025-12-31T17:45:00",
    "session_theatre": "Theatre 4",
    "session_key": "THR4_PM",
    "last_refresh_dttm": "2025-12-31T15:30:00"
  },
  {
    "case_start": "2025-12-31T08:43:00",
    "case_end": "2025-12-31T10:40:00",
    "case_status": "Complete",
    "case_procedure": "Total hip replacement",
    "session_start": "2025-12-31T08:30:00",
    "session_end": "2025-12-31T12:45:00",
    "session_theatre": "Theatre 5",
    "session_key": "THR5_AM",
    "last_refresh_dttm": "2025-12-31T15:30:00"
  },
  {
    "case_start": "2025-12-31T10:47:00",
    "case_end": "2025-12-31T12:07:00",
    "case_status": "Complete",
    "case_procedure": "Knee arthroscopy",
    "session_start": "2025-12-31T08:30:00",
    "session_end": "2025-12-31T12:45:00",
    "session_theatre": "Theatre 5",
    "session_key": "THR5_AM",
    "last_refresh_dttm": "2025-12-31T15:30:00"
  },
  {
    "case_start": "2025-12-31T12:20:00",
    "case_end": "2025-12-31T13:28:00",
    "case_status": "Complete",
    "case_procedure": "Rotator cuff repair",
    "session_start": "2025-12-31T08:30:00",
    "session_end": "2025-12-31T12:45:00",
    "session_theatre": "Theatre 5",
    "session_key": "THR5_AM",
    "last_refresh_dttm": "2025-12-31T15:30:00"
  },
  {
    "case_start": "2025-12-31T13:36:00",
    "case_end": "2025-12-31T14:31:00",
    "case_status": "Complete",
    "case_procedure": "ACL reconstruction",
    "session_start": "2025-12-31T13:30:00",
    "session_end": "2025-12-31T17:00:00",
    "session_theatre": "Theatre 5",
    "session_key": "THR5_PM",
    "last_refresh_dttm": "2025-12-31T15:30:00"
  },
  {
    "case_start": "2025-12-31T14:43:00",
    "case_end": null,
    "case_status": "In Progress",
    "case_procedure": "Revision total knee replacement",
    "session_start": "2025-12-31T13:30:00",
    "session_end": "2025-12-31T17:00:00",
    "session_theatre": "Theatre 5",
    "session_key": "THR5_PM",
    "last_refresh_dttm": "2025-12-31T15:30:00"
  },
  {
    "case_start": "2025-12-31T08:31:00",
    "case_end": "2025-12-31T09:34:00",
    "case_status": "Complete",
    "case_procedure": "Cataract extraction with lens implant",
    "session_start": "2025-12-31T08:30:00",
    "session_end": "2025-12-31T12:45:00",
    "session_theatre": "Theatre 6",
    "session_key": "THR6_AM",
    "last_refresh_dttm": "2025-12-31T15:30:00"
  },
  {
    "case_start": "2025-12-31T09:31:00",
    "case_end": "2025-12-31T10:57:00",
    "case_status": "Complete",
    "case_procedure": "Vitrectomy",
    "session_start": "2025-12-31T08:30:00",
    "session_end": "2025-12-31T12:45:00",
    "session_theatre": "Theatre 6",
    "session_key": "THR6_AM",
    "last_refresh_dttm": "2025-12-31T15:30:00"
  },
  {
    "case_start": "2025-12-31T13:37:00",
    "case_end": "2025-12-31T14:32:00",
    "case_status": "Complete",
    "case_procedure": "Trabeculectomy",
    "session_start": "2025-12-31T13:30:00",
    "session_end": "2025-12-31T17:45:00",
    "session_theatre": "Theatre 6",
    "session_key": "THR6_PM",
    "last_refresh_dttm": "2025-12-31T15:30:00"
  },
  {
    "case_start": "2025-12-31T14:33:00",
    "case_end": null,
    "case_status": "In Progress",
    "case_procedure": "Corneal graft",
    "session_start": "2025-12-31T13:30:00",
    "session_end": "2025-12-31T17:45:00",
    "session_theatre": "Theatre 6",
    "session_key": "THR6_PM",
    "last_refresh_dttm": "2025-12-31T15:30:00"
  },
  {
    "case_start": "2025-12-31T08:19:00",
    "case_end": "2025-12-31T09:20:00",
    "case_status": "Complete",
    "case_procedure": "Laparoscopic cholecystectomy",
    "session_start": "2025-12-31T08:30:00",
    "session_end": "2025-12-31T17:30:00",
    "session_theatre": "Theatre 7",
    "session_key": "THR7_ALLDAY",
    "last_refresh_dttm": "2025-12-31T15:30:00"
  },
  {
    "case_start": "2025-12-31T09:33:00",
    "case_end": "2025-12-31T11:06:00",
    "case_status": "Complete",
    "case_procedure": "Right hemicolectomy",
    "session_start": "2025-12-31T08:30:00",
    "session_end": "2025-12-31T17:30:00",
    "session_theatre": "Theatre 7",
    "session_key": "THR7_ALLDAY",
    "last_refresh_dttm": "2025-12-31T15:30:00"
  },
  {
    "case_start": "2025-12-31T11:04:00",
    "case_end": "2025-12-31T12:30:00",
    "case_status": "Complete",
    "case_procedure": "Laparoscopic inguinal hernia repair",
    "session_start": "2025-12-31T08:30:00",
    "session_end": "2025-12-31T17:30:00",
    "session_theatre": "Theatre 7",
    "session_key": "THR7_ALLDAY",
    "last_refresh_dttm": "2025-12-31T15:30:00"
  },
  {
    "case_start": "2025-12-31T12:37:00",
    "case_end": "2025-12-31T14:28:00",
    "case_status": "Complete",
    "case_procedure": "Anterior resection",
    "session_start": "2025-12-31T08:30:00",
    "session_end": "2025-12-31T17:30:00",
    "session_theatre": "Theatre 7",
    "session_key": "THR7_ALLDAY",
    "last_refresh_dttm": "2025-12-31T15:30:00"
  },
  {
    "case_start": "2025-12-31T14:35:00",
    "case_end": null,
    "case_status": "In Progress",
    "case_procedure": "Laparoscopic adhesiolysis",
    "session_start": "2025-12-31T08:30:00",
    "session_end": "2025-12-31T17:30:00",
    "session_theatre": "Theatre 7",
    "session_key": "THR7_ALLDAY",
    "last_refresh_dttm": "2025-12-31T15:30:00"
  },
  {
    "case_start": "2025-12-31T08:29:00",
    "case_end": "2025-12-31T09:38:00",
    "case_status": "Complete",
    "case_procedure": "Flexible cystoscopy",
    "session_start": "2025-12-31T08:30:00",
    "session_end": "2025-12-31T12:45:00",
    "session_theatre": "Theatre 8",
    "session_key": "THR8_AM",
    "last_refresh_dttm": "2025-12-31T15:30:00"
  },
  {
    "case_start": "2025-12-31T09:51:00",
    "case_end": "2025-12-31T10:49:00",
    "case_status": "Complete",
    "case_procedure": "Ureteroscopy and laser stone treatment",
    "session_start": "2025-12-31T08:30:00",
    "session_end": "2025-12-31T12:45:00",
    "session_theatre": "Theatre 8",
    "session_key": "THR8_AM",
    "last_refresh_dttm": "2025-12-31T15:30:00"
  },
  {
    "case_start": "2025-12-31T13:40:00",
    "case_end": "2025-12-31T14:52:00",
    "case_status": "Complete",
    "case_procedure": "Transurethral resection of bladder tumour",
    "session_start": "2025-12-31T13:30:00",
    "session_end": "2025-12-31T17:45:00",
    "session_theatre": "Theatre 8",
    "session_key": "THR8_PM",
    "last_refresh_dttm": "2025-12-31T15:30:00"
  },
  {
    "case_start": "2025-12-31T14:52:00",
    "case_end": null,
    "case_status": "In Progress",
    "case_procedure": "Radical nephrectomy",
    "session_start": "2025-12-31T13:30:00",
    "session_end": "2025-12-31T17:45:00",
    "session_theatre": "Theatre 8",
    "session_key": "THR8_PM",
    "last_refresh_dttm": "2025-12-31T15:30:00"
  }
]